{
  "_class": "symbolInstance",
  "do_objectID": "79A116C3-5896-4F7D-81C7-E27EC3BFB550",
  "exportOptions": {
    "_class": "exportOptions",
    "exportFormats": [
      {
        "_class": "exportFormat",
        "absoluteSize": 0,
        "fileFormat": "png",
        "name": "",
        "namingScheme": 0,
        "scale": 1,
        "visibleScaleType": 0
      },
      {
        "_class": "exportFormat",
        "absoluteSize": 0,
        "fileFormat": "png",
        "name": "@2x",
        "namingScheme": 0,
        "scale": 2,
        "visibleScaleType": 0
      },
      {
        "_class": "exportFormat",
        "absoluteSize": 0,
        "fileFormat": "png",
        "name": "@3x",
        "namingScheme": 0,
        "scale": 3,
        "visibleScaleType": 0
      }
    ],
    "includedLayerIds": [
    ],
    "layerOptions": 0,
    "shouldTrim": false
  },
  "frame": {
    "_class": "rect",
    "constrainProportions": false,
    "height": 38,
    "width": 48,
    "x": 164,
    "y": 398
  },
  "horizontalSpacing": 0,
  "isFlippedHorizontal": false,
  "isFlippedVertical": false,
  "isLocked": false,
  "isVisible": true,
  "layerListExpandedType": 0,
  "name": "-g-feedItemCard / ic / icCloseActionSheet",
  "nameIsFixed": false,
  "originalObjectID": "C49B6FFD-225F-454F-AE4A-36F7AB34F5DD",
  "overrideValues": [
  ],
  "resizingConstraint": 63,
  "resizingType": 0,
  "rotation": 0,
  "scale": 1,
  "shouldBreakMaskChain": false,
  "style": {
    "_class": "style",
    "endDecorationType": 0,
    "miterLimit": 10,
    "startDecorationType": 0
  },
  "symbolID": "214BD651-2C68-4D9F-9666-754F53AF5712",
  "verticalSpacing": 0
}