{
  "_class": "symbolInstance",
  "do_objectID": "4E0A531A-8C52-4C5C-84E5-D8496B7D8295",
  "exportOptions": {
    "_class": "exportOptions",
    "do_objectID": "8AFF08C8-9E2B-4180-8622-6B2660392DBD",
    "exportFormats": [
      {
        "_class": "exportFormat",
        "absoluteSize": 0,
        "fileFormat": "png",
        "name": "",
        "namingScheme": 0,
        "scale": 1,
        "visibleScaleType": 0
      },
      {
        "_class": "exportFormat",
        "absoluteSize": 0,
        "fileFormat": "png",
        "name": "@2x",
        "namingScheme": 0,
        "scale": 2,
        "visibleScaleType": 0
      },
      {
        "_class": "exportFormat",
        "absoluteSize": 0,
        "fileFormat": "png",
        "name": "@3x",
        "namingScheme": 0,
        "scale": 3,
        "visibleScaleType": 0
      }
    ],
    "includedLayerIds": [
    ],
    "layerOptions": 0,
    "shouldTrim": false
  },
  "frame": {
    "_class": "rect",
    "constrainProportions": false,
    "do_objectID": "F352D67C-9A99-43EE-88D1-3B6DFF9CF9A3",
    "height": 48,
    "width": 375,
    "x": 0,
    "y": 68
  },
  "horizontalSpacing": 0,
  "isFlippedHorizontal": false,
  "isFlippedVertical": false,
  "isLocked": false,
  "isVisible": true,
  "layerListExpandedType": 0,
  "name": "header / tagList",
  "nameIsFixed": false,
  "originalObjectID": "EC34676E-8076-4AC5-915D-2C01CE138F30",
  "overrideValues": [
  ],
  "resizingConstraint": 63,
  "resizingType": 0,
  "rotation": 0,
  "scale": 1,
  "shouldBreakMaskChain": false,
  "style": {
    "_class": "style",
    "do_objectID": "CADA89F4-E996-4883-AD91-4CDAE30BE2A3",
    "endDecorationType": 0,
    "miterLimit": 10,
    "startDecorationType": 0
  },
  "symbolID": "CF40F5E9-01E8-4B90-9E54-9E1E8127A0D5",
  "verticalSpacing": 0
}