{
  "_class": "symbolInstance",
  "do_objectID": "E1378EAD-813E-41B3-8DB8-68D9BA2D0BBA",
  "exportOptions": {
    "_class": "exportOptions",
    "do_objectID": "608A77CC-4DD8-467D-9C15-F0FF21B6F60C",
    "exportFormats": [
      {
        "_class": "exportFormat",
        "absoluteSize": 0,
        "fileFormat": "png",
        "name": "",
        "namingScheme": 0,
        "scale": 1,
        "visibleScaleType": 0
      },
      {
        "_class": "exportFormat",
        "absoluteSize": 0,
        "fileFormat": "png",
        "name": "@2x",
        "namingScheme": 0,
        "scale": 2,
        "visibleScaleType": 0
      },
      {
        "_class": "exportFormat",
        "absoluteSize": 0,
        "fileFormat": "png",
        "name": "@3x",
        "namingScheme": 0,
        "scale": 3,
        "visibleScaleType": 0
      }
    ],
    "includedLayerIds": [
    ],
    "layerOptions": 0,
    "shouldTrim": false
  },
  "frame": {
    "_class": "rect",
    "constrainProportions": false,
    "do_objectID": "1A197D9D-33B9-41E0-B2F8-56688662BAE2",
    "height": 48,
    "width": 375,
    "x": 0,
    "y": 68
  },
  "horizontalSpacing": 0,
  "isFlippedHorizontal": false,
  "isFlippedVertical": false,
  "isLocked": false,
  "isVisible": true,
  "layerListExpandedType": 0,
  "name": "header / tagList",
  "nameIsFixed": false,
  "originalObjectID": "3D969247-7B9F-405D-AFB3-604C07921632",
  "overrideValues": [
  ],
  "resizingConstraint": 63,
  "resizingType": 0,
  "rotation": 0,
  "scale": 1,
  "shouldBreakMaskChain": false,
  "style": {
    "_class": "style",
    "do_objectID": "D5DADAE7-633A-4388-9AB7-BB3386B6CAF7",
    "endDecorationType": 0,
    "miterLimit": 10,
    "startDecorationType": 0
  },
  "symbolID": "A9632075-E153-418C-B6FD-6248D3116D1C",
  "verticalSpacing": 0
}